simmer_sdk/__init__.py
simmer_sdk/approvals.py
simmer_sdk/client.py
simmer_sdk/signing.py
simmer_sdk-0.5.0.dist-info/LICENSE
simmer_sdk-0.5.0.dist-info/METADATA
simmer_sdk-0.5.0.dist-info/WHEEL
simmer_sdk-0.5.0.dist-info/top_level.txt
simmer_sdk-0.5.0.dist-info/RECORD
