Metadata-Version: 2.2
Name: simmer-sdk
Version: 0.5.0
Summary: Python SDK for trading prediction markets with AI agents - includes Clawbot trading skills
Author-email: Simmer <hello@simmer.markets>
Project-URL: Homepage, https://simmer.markets
Project-URL: Documentation, https://github.com/SpartanLabsXyz/simmer-sdk
Project-URL: Repository, https://github.com/SpartanLabsXyz/simmer-sdk
Project-URL: Issues, https://github.com/SpartanLabsXyz/simmer-sdk/issues
Project-URL: Skills, https://github.com/SpartanLabsXyz/simmer-sdk/tree/main/skills
Keywords: prediction-markets,polymarket,kalshi,trading,sdk
Classifier: Development Status :: 4 - Beta
Classifier: Intended Audience :: Developers
Classifier: License :: OSI Approved :: MIT License
Classifier: Programming Language :: Python :: 3
Classifier: Programming Language :: Python :: 3.8
Classifier: Programming Language :: Python :: 3.9
Classifier: Programming Language :: Python :: 3.10
Classifier: Programming Language :: Python :: 3.11
Classifier: Programming Language :: Python :: 3.12
Classifier: Topic :: Office/Business :: Financial :: Investment
Requires-Python: >=3.8
License-File: LICENSE
Requires-Dist: requests>=2.25.0
